src/__init__.py
src/__main__.py
src/course/__init__.py
src/course/db.py
src/course/main.py
src/serverPost/__init__.py
src/serverPost/main.py
src/teacherCourse/__init__.py
src/teacherCourse/db.py
src/teacherCourse/main.py
src/ulits/__init__.py
src/ulits/cookie.py
src/ulits/logo.py
pip_cache_purge-0.1.0.dist-info/LICENSE
pip_cache_purge-0.1.0.dist-info/METADATA
pip_cache_purge-0.1.0.dist-info/WHEEL
pip_cache_purge-0.1.0.dist-info/entry_points.txt
pip_cache_purge-0.1.0.dist-info/top_level.txt
pip_cache_purge-0.1.0.dist-info/RECORD
